README.rst
setup.py
nvimex/__init__.py
nvimex/nvimex.py
nvimex.egg-info/PKG-INFO
nvimex.egg-info/SOURCES.txt
nvimex.egg-info/dependency_links.txt
nvimex.egg-info/entry_points.txt
nvimex.egg-info/requires.txt
nvimex.egg-info/top_level.txt