Metadata-Version: 1.1
Name: nvimex
Version: 0.1
Summary: Run neovim commands from your shell.
Home-page: https://github.com/akarl818/nvimex
Author: Andreas Karlsson
Author-email: andreas.karlsson87+pip-nvimex@gmail.com
License: MIT
Keywords: neovim
Platform: UNKNOWN
Classifier: License :: OSI Approved :: MIT License
Classifier: Operating System :: OS Independent
Classifier: Programming Language :: Python :: 2.7
